{
    "device_type": "WiFi Router",
    "brand": "Allnet",
    "model": "ALL0305",
    "availability": "Discontinued",
    "supported_since_commit": "https://git.lede-project.org/?p=source.git;a=commit;h=5a694e09c8559cc257e5252cf2ca4af153215e30",
    "supported_since_rel": "10.03",
    "supported_current_rel": "18.06.2",
    "target": "ar71xx",
    "subtarget": "generic",
    "package_architecture": "mips_24kc",
    "bootloader": "RedBoot",
    "cpu": "Atheros AR7161",
    "cpu_cores": "1",
    "cpu_mhz": "680",
    "flash_mb": "8",
    "ram_mb": "64",
    "ethernet_gbit_ports": "1",
    "vlan": true,
    "wlan_hardware": "2x Atheros AR5413 (mini-PCI)",
    "wlan_24ghz": "b/g",
    "wlan_50ghz": "a",
    "wlan_driver": "ath5k",
    "power_supply": "PoE 802.3af",
    "device_page": "all0305",
    "forum_search": "ALL0305",
    "git_search": "ALL0305",
    "wikidevi_url": "https://wikidevi.com/wiki/Allnet_ALL0305",
    "firmware_openwrt_upgrade_url": "http://downloads.openwrt.org/releases/18.06.2/targets/ar71xx/generic/openwrt-18.06.2-ar71xx-generic-all0305-squashfs-sysupgrade.bin",
    "firmware_openwrt_snapshot_upgrade_url": "http://downloads.openwrt.org/snapshots/targets/ar71xx/generic/openwrt-ar71xx-generic-all0305-squashfs-sysupgrade.bin",
    "installation_method_s": "see devicepage"
}