{
    "device_type": "Modem",
    "brand": "D-Link",
    "model": "DSL-524T",
    "version": "A1 (EU)",
    "availability": "Discontinued",
    "supported_since_rel": "10.03.1",
    "supported_current_rel": "14.07",
    "target": "ar7",
    "subtarget": "generic",
    "package_architecture": "mipsel_mips32",
    "bootloader": "Adam2",
    "cpu": "Texas Instruments TNETD7300",
    "cpu_cores": "1",
    "cpu_mhz": "150",
    "flash_mb": "4",
    "ram_mb": "16",
    "ethernet_100m_ports": "4",
    "switch": "Infineon ADM6996M",
    "vlan": false,
    "modem": "ADSL2+ Annex A",
    "wlan_driver": "unknown",
    "serial": true,
    "serial_connection_parameters": "38400 / 8N1",
    "jtag": true,
    "led_count": "7",
    "button_count": "1",
    "power_supply": "12 VAC, 1.2 A",
    "device_page": "dsl-524t",
    "forum_search": "DSL-524T",
    "git_search": "DSL-524T",
    "oem_device_homepage_url": "http://www.dlink.com/uk/en/support/product/dsl-524t-4-port-adsl2-2-router",
    "firmware_oem_stock_url": "ftp://ftp.dlink.eu/Products/dsl/dsl-524t/driver_software/DSL-524T_fw_revA_310B01T02EUA20070613_ALL_en_20070613.zip",
    "firmware_openwrt_install_url": "http://downloads.openwrt.org/barrier_breaker/14.07/ar7/generic/openwrt-ar7-generic-squashfs.bin"
}