{
    "device_type": "WiFi Router",
    "brand": "Inventel",
    "model": "Livebox 1.2(Mini)",
    "version": "BlueDSL 8G",
    "availability": "unknown 2018",
    "unsupported_functions": "WIP",
    "target": "brcm63xx",
    "subtarget": "generic",
    "package_architecture": "mips_mips32",
    "cpu": "Broadcom BCM6358",
    "cpu_cores": "2",
    "cpu_mhz": "300",
    "flash_mb": "16",
    "ram_mb": "64",
    "vlan": false,
    "comments_network_ports": "5",
    "wlan_hardware": "Atheros AR5212 (mini-PCI)",
    "wlan_24ghz": "b/g",
    "wlan_driver": "unknown",
    "usb_ports": true,
    "forum_search": "Livebox 1.2(Mini)",
    "git_search": "Livebox 1.2(Mini)"
}