{
    "device_type": "Router",
    "brand": "Linksys",
    "model": "AG241",
    "version": "v1",
    "availability": "Discontinued",
    "supported_since_rel": "8.09.2",
    "supported_current_rel": "10.03.1",
    "target": "ar7",
    "package_architecture": "mipsel_mips32",
    "bootloader": "PSPBoot",
    "cpu": "Texas Instruments TNETD7200ZDW",
    "cpu_cores": "1",
    "cpu_mhz": "212",
    "flash_mb": "4",
    "ram_mb": "16",
    "ethernet_100m_ports": "4",
    "vlan": false,
    "modem": "xDSL",
    "device_page": "ag241",
    "forum_search": "AG241",
    "git_search": "AG241",
    "comment_installation": "For TFTP, rename OpenWrt image to upgrade_code.bin",
    "comment_recovery": "For TFTP, rename OpenWrt image to upgrade_code.bin"
}