{
    "device_type": "Single Board Computer",
    "brand": "Evaluation boards / unbranded boards",
    "model": "Marvell DB-A380-DDR3-AP",
    "availability": "unknown 2018",
    "supported_since_commit": "https://git.lede-project.org/?p=source.git;a=commit;h=66e35c52467cde2fff7c3148b3c3e0f668fb9721",
    "supported_since_rel": "15.05",
    "supported_current_rel": "17.01.4",
    "target": "mvebu",
    "subtarget": "generic",
    "package_architecture": "arm_cortex-a9_vfpv3",
    "cpu": "Marvell Armada 38x",
    "cpu_cores": "2",
    "cpu_mhz": "1600",
    "flash_mb": "1024NAND",
    "ram_mb": "2048",
    "ethernet_gbit_ports": "3",
    "wlan_hardware": "3x mini-PCIe",
    "wlan_driver": "unknown",
    "forum_search": "Marvell DB-A380-DDR3-AP",
    "git_search": "Marvell DB-A380-DDR3-AP",
    "firmware_openwrt_install_url": "http://downloads.lede-project.org/releases/17.01.4/targets/mvebu/generic/",
    "firmware_openwrt_upgrade_url": "http://downloads.lede-project.org/releases/17.01.4/targets/mvebu/generic/",
    "installation_method_s": "unknown",
    "recovery_method_s": "unknown"
}